pseudocode/__init__.py
pseudocode/builtin.py
pseudocode/interpreter.py
pseudocode/lang.py
pseudocode/parser.py
pseudocode/resolver.py
pseudocode/scanner.py
pseudocode/system.py
pseudo_9608-0.4.1.dist-info/entry_points.txt
pseudo_9608-0.4.1.dist-info/LICENSE
pseudo_9608-0.4.1.dist-info/WHEEL
pseudo_9608-0.4.1.dist-info/METADATA
pseudo_9608-0.4.1.dist-info/RECORD
