Metadata-Version: 2.1
Name: pseudo-9608
Version: 0.4.1
Summary: An interpreter for 9608 pseudocode
Home-page: https://github.com/nyjc-computing/pseudo-9608
License: MIT
Author: JS Ng
Author-email: ngjunsiang@gmail.com
Requires-Python: >=3.8,<4.0
Classifier: License :: OSI Approved :: MIT License
Classifier: Programming Language :: Python :: 3
Classifier: Programming Language :: Python :: 3.10
Classifier: Programming Language :: Python :: 3.8
Classifier: Programming Language :: Python :: 3.9
Project-URL: Repository, https://github.com/nyjc-computing/pseudo-9608.git
